code_editor/__init__.py
code_editor/frontend/build/014d84e08c5a2ee1b019d81a57f69b6d.js
code_editor/frontend/build/021b7834b70164d3cbd6b4bd838d26e7.js
code_editor/frontend/build/0240d9d226aaba17854215eb48a7a349.js
code_editor/frontend/build/02e46277d075a9c677f8e6c3ec611a1c.js
code_editor/frontend/build/02f7464c0789a7cbd29fd48f80d377ab.js
code_editor/frontend/build/03325b4ae8405296dacf9ae05e26531f.js
code_editor/frontend/build/03b6f5ed432b1096271448f530f79c3a.js
code_editor/frontend/build/051172af4df2228c8acf8d04d449ab1d.js
code_editor/frontend/build/05b6f2cd8f995ebfe6a88e2c5c94f18b.js
code_editor/frontend/build/05f2b6d27716f95c75421370d5ee9029.js
code_editor/frontend/build/061367bf16cebaa213578275d117ecb4.js
code_editor/frontend/build/06dc01c590f035472ea43f56906f5b04.js
code_editor/frontend/build/06e5228026941b35022f84005f69fa2f.js
code_editor/frontend/build/07011752aeaa58913a688453ba034167.js
code_editor/frontend/build/07de343f3a3a86b4c67e887239399197.js
code_editor/frontend/build/09ae210b6db3c61084590d1052f08765.js
code_editor/frontend/build/09b692bdd107a162d70e85daf94a3fb6.js
code_editor/frontend/build/0a3f85997947fcc989b003237e68e745.js
code_editor/frontend/build/0a4438ad4f6617ec42fb006d2c3da2ad.js
code_editor/frontend/build/0a459948dae1290356f3d6e3d656a56b.js
code_editor/frontend/build/0a84849cb72c84fb6a9b4d831df64ffa.js
code_editor/frontend/build/0adaf0cf553f3428e44a6d4f8207d477.js
code_editor/frontend/build/0b165878ec4512fb75837abc4cb50b4e.js
code_editor/frontend/build/0b8338fc8d3aaca740fc159cd65dfa0e.js
code_editor/frontend/build/0bbdfc82acc2ea66ba14ad4c65193773.js
code_editor/frontend/build/0c14e3f2bbdb026c7dbdecf587f1df62.js
code_editor/frontend/build/0c93349d05810059db73cafb8956afd5.js
code_editor/frontend/build/0d030581fbdd078214634bf71575a540.js
code_editor/frontend/build/0d03ede352818bc887604f4b22e105be.js
code_editor/frontend/build/0d23aba2dc82c8a5b2c908efb76d1b53.js
code_editor/frontend/build/0db473c88fdf68a9b6cec96a21ef604f.js
streamlit_code_editor-0.1.22.dist-info/LICENSE
streamlit_code_editor-0.1.22.dist-info/METADATA
streamlit_code_editor-0.1.22.dist-info/WHEEL
streamlit_code_editor-0.1.22.dist-info/top_level.txt
streamlit_code_editor-0.1.22.dist-info/RECORD
