Metadata-Version: 2.1
Name: streamlit-code-editor
Version: 0.1.22
Summary: React-ace editor customized for Streamlit
Home-page: https://github.com/bouzidanas/streamlit-code-editor
Author: Anas Bouzid
Author-email: anasbouzid@gmail.com
Requires-Python: >=3.6
License-File: LICENSE
